{
	"design__max_slew_violation__count__corner:nom_tt_025C_1v80": 0,
	"design__max_fanout_violation__count__corner:nom_tt_025C_1v80": 17,
	"design__max_cap_violation__count__corner:nom_tt_025C_1v80": 0,
	"power__internal__total": 0.00164556,
	"power__switching__total": 0.000484108,
	"power__leakage__total": 8.75416e-09,
	"power__total": 0.00212968,
	"clock__skew__worst_hold__corner:nom_tt_025C_1v80": -0.276989,
	"clock__skew__worst_setup__corner:nom_tt_025C_1v80": 0.274895,
	"timing__hold__ws__corner:nom_tt_025C_1v80": 0.13828,
	"timing__setup__ws__corner:nom_tt_025C_1v80": 6.17673,
	"timing__hold__tns__corner:nom_tt_025C_1v80": 0,
	"timing__setup__tns__corner:nom_tt_025C_1v80": 0,
	"timing__hold__wns__corner:nom_tt_025C_1v80": 0,
	"timing__setup__wns__corner:nom_tt_025C_1v80": 0,
	"timing__hold_vio__count__corner:nom_tt_025C_1v80": 0,
	"timing__hold_r2r__ws__corner:nom_tt_025C_1v80": 0.13828,
	"timing__hold_r2r_vio__count__corner:nom_tt_025C_1v80": 0,
	"timing__setup_vio__count__corner:nom_tt_025C_1v80": 0,
	"timing__setup_r2r__ws__corner:nom_tt_025C_1v80": 7.00837,
	"timing__setup_r2r_vio__count__corner:nom_tt_025C_1v80": 0,
	"flow__warnings__count": 0,
	"flow__errors__count": 0,
	"flow__warnings__type_count": 0
}